{"title": "+ \u5173\u4e8e\u516c\u5e032016\u5e74\u56db\u5ddd\u5927\u5b66\u529b\u5b66\u7ade\u8d5b\uff08\u56db\u5ddd\u7701\u5b59\u8bad\u65b9\u5927\u5b66\u751f\u529b\u5b66\u7ade\u8d5b\u9009\u62d4\u8d5b\uff09\u83b7\u5956\u540d\u5355\u7684\u901a\u77e5", "content": "<p> \u5404\u5b66\u9662\u53ca\u76f8\u5173\u540c\u5b66\uff1a </p> \n<p class=\"MsoNormal\" style=\"text-indent:27.75pt;\"> 2016\u5e74\u56db\u5ddd\u5927\u5b66\u529b\u5b66\u7ade\u8d5b\u4e8e10\u670823\u65e5\u5706\u6ee1\u7ed3\u675f\uff0c\u5171\u670965\u4f4d\u540c\u5b66\u83b7\u5956\uff08\u89c1\u9644\u4ef62\uff09\u5e76\u540c\u65f6\u83b7\u5f97\u4ee3\u8868\u56db\u5ddd\u5927\u5b66\u53c2\u52a02016\u5e74\u56db\u5ddd\u7701\u5927\u5b66\u751f\u529b\u5b66\u7ade\u8d5b\u7684\u53c2\u8d5b\u8d44\u683c\u3002\u56db\u5ddd\u7701\u5927\u5b66\u751f\u529b\u5b66\u7ade\u8d5b\u65f6\u95f4\u4e3a2016\u5e7411\u670826\u65e5\uff08\u661f\u671f\u516d\uff09\u4e0a\u53489\uff1a00 \u2014 <span>12</span>\uff1a00\uff0c\u5730\u70b9\u4e3a\u897f\u5357\u4ea4\u901a\u5927\u5b66\u7280\u6d66\u6821\u533a\uff0c\u5c4a\u65f6\u6211\u6821\u5c06\u6d3e\u8f66\u63a5\u9001\uff0c\u5177\u4f53\u4e58\u8f66\u65f6\u95f4\u5730\u70b9\u89c1\u540e\u7eed\u901a\u77e5\uff0c\u76f8\u5173\u8d5b\u4e8b\u901a\u77e5\u89c1\u9644\u4ef61\u3002 </p> \n<p class=\"MsoNormal\" style=\"text-indent:27.75pt;\"> &nbsp; </p> \n<p class=\"MsoNormal\" style=\"text-indent:27.75pt;\"> &nbsp;<a class=\"ke-insertfile\" href=\"http://acem.scu.edu.cn/uploads/image/20161102/1478090803.pdf\" target=\"_blank\">\u9644\u4ef61\uff1a2016\u5e74\u56db\u5ddd\u7701\u5927\u5b66\u751f\u529b\u5b66\u7ade\u8d5b\u901a\u77e5</a> </p> \n<p class=\"MsoNormal\" style=\"text-indent:27.75pt;\"> &nbsp;<a class=\"ke-insertfile\" href=\"http://acem.scu.edu.cn/uploads/soft/20161102/1478087832.xls\" target=\"_blank\">\u9644\u4ef62\uff1a2016\u5e74\u56db\u5ddd\u5927\u5b66\u529b\u5b66\u7ade\u8d5b\u83b7\u5956\u540d\u5355</a> </p> \n<p class=\"MsoNormal\" style=\"text-indent:27.75pt;\"> &nbsp; </p> \n<p class=\"MsoNormal\" style=\"text-indent:27.75pt;\"> &nbsp; </p> \n<p class=\"MsoNormal\" style=\"text-indent:27.75pt;\"> <span>&nbsp;</span> </p> \n<p align=\"right\" style=\"text-align:right;\"> \u56db\u5ddd\u5927\u5b66\u529b\u5b66\u7ade\u8d5b\u7ec4\u59d4\u4f1a </p> 2016\u5e7411\u67082\u65e5", "id": 24, "category": "Notice", "originURL": "http://acem.scu.edu.cn/newsshow.php?cid=88&id=11044", "academy": "\u5efa\u7b51\u4e0e\u73af\u5883\u5b66\u9662", "time": "2016-11-02T10:33:11Z"}